devpi_ext/__init__.py
devpi_ext/login.py
devpi_ext/py.typed
devpi_client_extensions-0.3.1.dist-info/entry_points.txt
devpi_client_extensions-0.3.1.dist-info/LICENSE
devpi_client_extensions-0.3.1.dist-info/WHEEL
devpi_client_extensions-0.3.1.dist-info/METADATA
devpi_client_extensions-0.3.1.dist-info/RECORD
