Metadata-Version: 2.1
Name: devpi-client-extensions
Version: 0.3.1
Summary: devpi client extensions
Home-page: https://github.com/hoefling/devpi-client-extensions
License: MIT
Author: Oleg Höfling
Author-email: oleg.hoefling@gmail.com
Requires-Python: >=3.6,<4.0
Classifier: Development Status :: 3 - Alpha
Classifier: Environment :: Web Environment
Classifier: Intended Audience :: Developers
Classifier: Intended Audience :: System Administrators
Classifier: License :: OSI Approved :: MIT License
Classifier: Programming Language :: Python :: 3
Classifier: Programming Language :: Python :: 3.6
Classifier: Programming Language :: Python :: 3.7
Classifier: Programming Language :: Python :: 3.8
Classifier: Programming Language :: Python :: 3.9
Classifier: Programming Language :: Python :: Implementation
Provides-Extra: keyring
Requires-Dist: devpi-client (>=3.0.0)
Requires-Dist: importlib-metadata (>=1.5.0,<2.0.0); python_version < "3.8"
Requires-Dist: keyring; extra == "keyring"
Project-URL: Repository, https://github.com/hoefling/devpi-client-extensions
